metest/__init__.py
metest/__main__.py
metest/datametric.py
metest/logmetric.py
metest-0.0.1.dist-info/LICENSE
metest-0.0.1.dist-info/METADATA
metest-0.0.1.dist-info/WHEEL
metest-0.0.1.dist-info/top_level.txt
metest-0.0.1.dist-info/RECORD
