Metadata-Version: 2.1
Name: metest
Version: 0.0.1
Summary: Test, check and compare logs and data from meteorological computations.
Home-page: https://dmidk.github.io/metest/
Author: Kasper Hintz
Author-email: kah@dmi.dk
License: UNKNOWN
Platform: UNKNOWN
Classifier: Programming Language :: Python :: 3
Classifier: License :: OSI Approved :: MIT License
Classifier: Operating System :: OS Independent
License-File: LICENSE
